blacs/__init__.py
blacs/__main__.py
blacs/__version__.py
blacs/analysis_submission.py
blacs/analysis_submission.ui
blacs/blacs.ico
blacs/blacs.svg
blacs/compile_and_restart.py
blacs/compile_and_restart.ui
blacs/desktop-app.json
blacs/device_base_class.py
blacs/experiment_queue.py
blacs/front_panel_settings.py
blacs/main.ui
blacs/notification_minimized_widget.ui
blacs/notification_widget.ui
blacs/notifications.py
blacs/output_classes.py
blacs/plugin_tab_frame.ui
blacs/tab_base_classes.py
blacs/tab_frame.ui
blacs/tab_value_changed.ui
blacs/tab_value_changed_dds.ui
blacs/measure_ball/D3DX9_43.dll
blacs/measure_ball/LICENSE
blacs/measure_ball/RabiBall.exe
blacs/measure_ball/data.win
blacs/measure_ball/options.ini
blacs/measure_ball/snd_mus_super_quantised_song.ogg
blacs/measure_ball/splash.png
blacs/plugins/__init__.py
blacs/plugins/connection_table/__init__.py
blacs/plugins/connection_table/broken_device_notification.ui
blacs/plugins/connection_table/connection_table.ui
blacs/plugins/connection_table/notification.ui
blacs/plugins/cycle_time/__init__.py
blacs/plugins/delete_repeated_shots/__init__.py
blacs/plugins/delete_repeated_shots/controls.ui
blacs/plugins/general/__init__.py
blacs/plugins/general/general.ui
blacs/plugins/memory/__init__.py
blacs/plugins/progress_bar/__init__.py
blacs/plugins/progress_bar/controls.ui
blacs/plugins/theme/__init__.py
blacs/plugins/theme/theme.ui
blacs-3.2.3.dist-info/licenses/LICENSE.txt
blacs-3.2.3.dist-info/METADATA
blacs-3.2.3.dist-info/WHEEL
blacs-3.2.3.dist-info/entry_points.txt
blacs-3.2.3.dist-info/top_level.txt
blacs-3.2.3.dist-info/RECORD
