Metadata-Version: 2.4
Name: blacs
Version: 3.2.3
Summary: Graphical labscript suite experiment queue and hardware interface
Author-email: The labscript suite community <labscriptsuite@googlegroups.com>
License: Copyright (c) 2013, Monash University
Project-URL: Homepage, http://labscriptsuite.org/
Project-URL: Documentation, https://docs.labscriptsuite.org/
Project-URL: Repository, https://github.com/labscript-suite/blacs/
Project-URL: Downloads, https://github.com/labscript-suite/blacs/releases/
Project-URL: Tracker, https://github.com/labscript-suite/blacs/issues/
Keywords: experiment control,automation
Classifier: License :: OSI Approved :: BSD License
Classifier: Programming Language :: Python :: 3 :: Only
Requires-Python: >=3.8
License-File: LICENSE.txt
Requires-Dist: desktop-app>=0.1.2
Requires-Dist: labscript_utils>=3.1.0b1
Requires-Dist: runmanager>=3.0.0
Requires-Dist: qtutils>=2.2.2
Requires-Dist: zprocess>=2.14.1
Provides-Extra: docs
Requires-Dist: PyQt5; extra == "docs"
Requires-Dist: Sphinx==8.2.3; extra == "docs"
Requires-Dist: sphinx-rtd-theme==3.0.2; extra == "docs"
Requires-Dist: myst_parser==4.0.1; extra == "docs"
Dynamic: license-file
